nnfpy/__init__.py
nnfpy/costs.py
nnfpy/learningrate.py
nnfpy/layers/__init__.py
nnfpy/layers/fullyconnected/__init__.py
nnfpy/layers/speciallayers/__init__.py
nnfpy/network/__init__.py
nnfpy/network/onednet.py
nnfpy-1.2.0.dist-info/LICENSE.txt
nnfpy-1.2.0.dist-info/METADATA
nnfpy-1.2.0.dist-info/WHEEL
nnfpy-1.2.0.dist-info/top_level.txt
nnfpy-1.2.0.dist-info/RECORD
