Metadata-Version: 2.1
Name: nnfpy
Version: 1.2.0
Summary: Neural network for python
Home-page: https://github.com/sopho-s/nnfpy
Author: Nick Woods, Olivier Hinds
Author-email: woodsnicholas01@gmail.com
License: MIT
Platform: UNKNOWN
Classifier: License :: OSI Approved :: MIT License
Classifier: Programming Language :: Python :: 3
Classifier: Programming Language :: Python :: 3.9
License-File: LICENSE.txt
